LICENSE
README.md
setup.py
asyncio_rabbitmq_consumer/__init__.py
asyncio_rabbitmq_consumer.egg-info/PKG-INFO
asyncio_rabbitmq_consumer.egg-info/SOURCES.txt
asyncio_rabbitmq_consumer.egg-info/dependency_links.txt
asyncio_rabbitmq_consumer.egg-info/requires.txt
asyncio_rabbitmq_consumer.egg-info/top_level.txt