Metadata-Version: 1.0
Name: asyncio-rabbitmq-consumer
Version: 0.1.1
Summary: Base rabbitmq consumer for asyncio
Home-page: https://github.com/dmonroy/asyncio-rabbitmq-consumer
Author: Darwin Monroy
Author-email: contact@darwinmonroy.com
License: MIT License
Platform: UNKNOWN
